vns_explorer/__init__.py
vns_explorer/agent.py
vns_explorer/browser.py
vns_explorer/env.py
vns_explorer-1.0.6.dist-info/METADATA
vns_explorer-1.0.6.dist-info/WHEEL
vns_explorer-1.0.6.dist-info/top_level.txt
vns_explorer-1.0.6.dist-info/RECORD
