Metadata-Version: 2.1
Name: vns_explorer
Version: 1.0.6
Summary: Discover the Unseen
Author: Thinh Vu
Author-email: Thinh Vu <mrthinh@live.com>
Classifier: Programming Language :: Python :: 3
Classifier: License :: OSI Approved :: MIT License
Classifier: Operating System :: OS Independent
Requires-Python: >=3.10
Requires-Dist: requests
Requires-Dist: webdriver-manager
Provides-Extra: dev
Requires-Dist: flake8 ; extra == 'dev'
Provides-Extra: test
Requires-Dist: unittest ; extra == 'test'
